signingsavvy/__init__.py
signingsavvy/__version__.py
signingsavvy/api.py
signingsavvy-1.0.7.dist-info/LICENSE
signingsavvy-1.0.7.dist-info/WHEEL
signingsavvy-1.0.7.dist-info/METADATA
signingsavvy-1.0.7.dist-info/RECORD
