Metadata-Version: 2.1
Name: signingsavvy
Version: 1.0.7
Summary: SigningSavvy API wrapper
Home-page: https://blackboardd.github.io/signingsavvy/
License: MIT
Keywords: Rest,ASL,Sign Language,API,SigningSavvy
Author: Brighten Tompkins
Author-email: brightenqtompkins@gmail.com
Maintainer: Brighten Tompkins
Maintainer-email: brightenqtompkins@gmail.com
Requires-Python: >=3.7,<4.0
Classifier: License :: OSI Approved :: MIT License
Classifier: Programming Language :: Python :: 3
Classifier: Programming Language :: Python :: 3.10
Classifier: Programming Language :: Python :: 3.7
Classifier: Programming Language :: Python :: 3.8
Classifier: Programming Language :: Python :: 3.9
Requires-Dist: bs4 (>=0.0.1,<0.0.2)
Requires-Dist: poetry-core (>=1.0.7,<2.0.0)
Requires-Dist: quart (>=0.16.2,<0.17.0)
Requires-Dist: requests (>=2.26.0,<3.0.0)
Requires-Dist: virtualenv (>=20.10.0,<21.0.0)
Project-URL: Documentation, https://blackboardd.github.io/signingsavvy/
Project-URL: Repository, https://github.com/blackboardd/signingsavvy
